big_num_format/__init__.py
big_num_format/big_num_format.py
big_num_format/symbols.txt
big_num_format/words.txt
big_num_format-0.4.dist-info/LICENSE
big_num_format-0.4.dist-info/METADATA
big_num_format-0.4.dist-info/WHEEL
big_num_format-0.4.dist-info/top_level.txt
big_num_format-0.4.dist-info/RECORD
