Metadata-Version: 2.1
Name: big-num-format
Version: 0.4
Summary: A package to convert very large numbers into human readable text.
Home-page: https://github.com/MBmasher/big-num-format
Author: MBmasher
Author-email: mbmasher@gmail.com
License: UNKNOWN
Platform: UNKNOWN
Classifier: Programming Language :: Python :: 3
Classifier: Operating System :: OS Independent
